bcoscli/__init__.py
bcoscli/commands.py
bcoscli/config.py
bcoscli-0.0.1.dist-info/LICENSE
bcoscli-0.0.1.dist-info/METADATA
bcoscli-0.0.1.dist-info/WHEEL
bcoscli-0.0.1.dist-info/entry_points.txt
bcoscli-0.0.1.dist-info/top_level.txt
bcoscli-0.0.1.dist-info/RECORD
