Metadata-Version: 2.1
Name: bcoscli
Version: 0.0.1
Summary: A userful package to use 'FISCO-BCOS', the FISCO-BCOS sdk
Home-page: https://github.com/Yyonging/bcoscli
Author: duanyongqiang
Author-email: sysuduanyongqiang@163.com
License: Apache License 2.0
Platform: UNKNOWN
Classifier: Programming Language :: Python :: 3
Classifier: License :: OSI Approved :: GNU General Public License v2 (GPLv2)
Classifier: Operating System :: OS Independent
Requires-Python: >=3.6
Requires-Dist: cod (>=0.0.3)
